{
  "timestamp": "2026-04-27T08:59:38.054265",
  "status": "OK",
  "stats": {
    "equity": 100363.2,
    "cash": 99683.54,
    "total_pnl": 363.2,
    "total_pnl_pct": 0.36,
    "num_positions": 10,
    "day_pnl": -40.17
  },
  "positions": [
    {
      "asset_id": "cfd74ad0-f301-495c-8423-429daa6f35c0",
      "symbol": "APLS",
      "exchange": "NASDAQ",
      "asset_class": "us_equity",
      "asset_marginable": true,
      "qty": "2",
      "qty_available": "0",
      "avg_entry_price": "40.4",
      "side": "long",
      "market_value": "81.88",
      "cost_basis": "80.8",
      "unrealized_pl": "1.08",
      "unrealized_plpc": "0.01337",
      "unrealized_intraday_pl": "0",
      "unrealized_intraday_plpc": "0",
      "current_price": "40.94",
      "lastday_price": "40.94",
      "change_today": "0"
    },
    {
      "asset_id": "49728256-228e-4516-9cc4-54d2d36b2f70",
      "symbol": "CYCN",
      "exchange": "NASDAQ",
      "asset_class": "us_equity",
      "asset_marginable": true,
      "qty": "34",
      "qty_available": "0",
      "avg_entry_price": "2.91",
      "side": "long",
      "market_value": "98.94",
      "cost_basis": "98.94",
      "unrealized_pl": "0",
      "unrealized_plpc": "0",
      "unrealized_intraday_pl": "-1.02",
      "unrealized_intraday_plpc": "-0.0102",
      "current_price": "2.91",
      "lastday_price": "2.94",
      "change_today": "-0.0102"
    },
    {
      "asset_id": "db4c8f34-b59c-4c26-a143-5e607afd4a1f",
      "symbol": "FLWS",
      "exchange": "NASDAQ",
      "asset_class": "us_equity",
      "asset_marginable": true,
      "qty": "12",
      "qty_available": "0",
      "avg_entry_price": "3.81",
      "side": "long",
      "market_value": "44.8812",
      "cost_basis": "45.72",
      "unrealized_pl": "-0.8388",
      "unrealized_plpc": "-0.01835",
      "unrealized_intraday_pl": "1.5612",
      "unrealized_intraday_plpc": "0.03604",
      "current_price": "3.7401",
      "lastday_price": "3.61",
      "change_today": "0.03604"
    },
    {
      "asset_id": "69e31b98-c3ae-45e1-9d31-6fca3f601443",
      "symbol": "IYT",
      "exchange": "BATS",
      "asset_class": "us_equity",
      "asset_marginable": true,
      "qty": "1",
      "qty_available": "0",
      "avg_entry_price": "75.85",
      "side": "long",
      "market_value": "81.52",
      "cost_basis": "75.85",
      "unrealized_pl": "5.67",
      "unrealized_plpc": "0.07475",
      "unrealized_intraday_pl": "0.17",
      "unrealized_intraday_plpc": "0.00209",
      "current_price": "81.52",
      "lastday_price": "81.35",
      "change_today": "0.00209"
    },
    {
      "asset_id": "606d8399-7cf9-496f-ae5f-312e937412d9",
      "symbol": "LFVN",
      "exchange": "NASDAQ",
      "asset_class": "us_equity",
      "asset_marginable": true,
      "qty": "12",
      "qty_available": "0",
      "avg_entry_price": "5.17",
      "side": "long",
      "market_value": "71.5188",
      "cost_basis": "62.04",
      "unrealized_pl": "9.4788",
      "unrealized_plpc": "0.15279",
      "unrealized_intraday_pl": "10.5588",
      "unrealized_intraday_plpc": "0.17321",
      "current_price": "5.9599",
      "lastday_price": "5.08",
      "change_today": "0.17321"
    },
    {
      "asset_id": "8efcac96-7f62-4114-a37f-5925ca791aae",
      "symbol": "MAXN",
      "exchange": "NASDAQ",
      "asset_class": "us_equity",
      "asset_marginable": false,
      "qty": "88",
      "qty_available": "88",
      "avg_entry_price": "1.12",
      "side": "long",
      "market_value": "85.36",
      "cost_basis": "98.56",
      "unrealized_pl": "-13.2",
      "unrealized_plpc": "-0.13393",
      "unrealized_intraday_pl": "-45.76",
      "unrealized_intraday_plpc": "-0.34899",
      "current_price": "0.97",
      "lastday_price": "1.49",
      "change_today": "-0.34899"
    },
    {
      "asset_id": "664a0bfd-263e-4109-b0a1-e9ee2564026b",
      "symbol": "MPLX",
      "exchange": "NYSE",
      "asset_class": "us_equity",
      "asset_marginable": true,
      "qty": "1",
      "qty_available": "0",
      "avg_entry_price": "56.04",
      "side": "long",
      "market_value": "54.77",
      "cost_basis": "56.04",
      "unrealized_pl": "-1.27",
      "unrealized_plpc": "-0.02266",
      "unrealized_intraday_pl": "-0.57",
      "unrealized_intraday_plpc": "-0.0103",
      "current_price": "54.77",
      "lastday_price": "55.34",
      "change_today": "-0.0103"
    },
    {
      "asset_id": "cd86ed39-216e-4e04-a3f0-9beea87fdf71",
      "symbol": "SKLZ",
      "exchange": "NYSE",
      "asset_class": "us_equity",
      "asset_marginable": true,
      "qty": "8",
      "qty_available": "0",
      "avg_entry_price": "7.71",
      "side": "long",
      "market_value": "61.3608",
      "cost_basis": "61.68",
      "unrealized_pl": "-0.3192",
      "unrealized_plpc": "-0.00518",
      "unrealized_intraday_pl": "-1.9192",
      "unrealized_intraday_plpc": "-0.03033",
      "current_price": "7.6701",
      "lastday_price": "7.91",
      "change_today": "-0.03033"
    },
    {
      "asset_id": "8158869b-a3ad-4ec2-9082-1bb195a6782a",
      "symbol": "SPCE",
      "exchange": "NYSE",
      "asset_class": "us_equity",
      "asset_marginable": false,
      "qty": "39",
      "qty_available": "39",
      "avg_entry_price": "2.55",
      "side": "long",
      "market_value": "97.4259",
      "cost_basis": "99.45",
      "unrealized_pl": "-2.0241",
      "unrealized_plpc": "-0.02035",
      "unrealized_intraday_pl": "-3.1941",
      "unrealized_intraday_plpc": "-0.03174",
      "current_price": "2.4981",
      "lastday_price": "2.58",
      "change_today": "-0.03174"
    },
    {
      "asset_id": "b28f4066-5c6d-479b-a2af-85dc1a8f16fb",
      "symbol": "SPY",
      "exchange": "ARCA",
      "asset_class": "us_equity",
      "asset_marginable": true,
      "qty": "0.002804536",
      "qty_available": "0.002804536",
      "avg_entry_price": "713.13",
      "side": "long",
      "market_value": "2.000784",
      "cost_basis": "1.999999",
      "unrealized_pl": "0.000785",
      "unrealized_plpc": "0.00039",
      "unrealized_intraday_pl": "0.000785",
      "unrealized_intraday_plpc": "0.00039",
      "current_price": "713.4101",
      "lastday_price": "713.94",
      "change_today": "-0.00074"
    }
  ]
}